frappe_auth_bridge/__init__.py
frappe_auth_bridge/cache.py
frappe_auth_bridge/core.py
frappe_auth_bridge/decorators/__init__.py
frappe_auth_bridge/decorators/auth.py
frappe_auth_bridge/exceptions.py
frappe_auth_bridge/middleware/__init__.py
frappe_auth_bridge/middleware/django.py
frappe_auth_bridge/middleware/fastapi.py
frappe_auth_bridge/middleware/flask.py
frappe_auth_bridge/models.py
frappe_auth_bridge/security.py
frappe_auth_bridge/session.py
frappe_auth_bridge/utils/__init__.py
frappe_auth_bridge/utils/async_client.py
frappe_auth_bridge/utils/logger.py
frappe_auth_bridge-0.2.3.dist-info/LICENSE
frappe_auth_bridge-0.2.3.dist-info/METADATA
frappe_auth_bridge-0.2.3.dist-info/WHEEL
frappe_auth_bridge-0.2.3.dist-info/RECORD
