Metadata-Version: 2.1
Name: frappe-auth-bridge
Version: 0.2.3
Summary: A Python authentication bridge that integrates with frappe-client to enable SSO across Django, Flask, FastAPI, and vanilla Python apps
Home-page: https://github.com/mymi14s/frappe-auth-bridge
License: MIT
Author: Anthony
Requires-Python: >=3.11,<4.0
Classifier: License :: OSI Approved :: MIT License
Classifier: Operating System :: OS Independent
Classifier: Programming Language :: Python :: 3
Classifier: Programming Language :: Python :: 3.11
Classifier: Programming Language :: Python :: 3.12
Classifier: Programming Language :: Python :: 3.13
Classifier: Programming Language :: Python :: 3.14
Provides-Extra: all
Provides-Extra: django
Provides-Extra: fastapi
Provides-Extra: flask
Provides-Extra: redis
Requires-Dist: cachetools (>=5.3.0,<6.0.0)
Requires-Dist: cryptography (>=42.0.0,<43.0.0)
Requires-Dist: django (>=5.0.0,<6.0.0) ; extra == "django" or extra == "all"
Requires-Dist: fastapi (>=0.109.0,<0.110.0) ; extra == "fastapi" or extra == "all"
Requires-Dist: flask (>=3.0.0,<4.0.0) ; extra == "flask" or extra == "all"
Requires-Dist: frappeclient (==0.1.0.dev0)
Requires-Dist: httpx (>=0.27.0,<0.28.0)
Requires-Dist: pydantic (>=2.6.0,<3.0.0)
Requires-Dist: redis (>=5.0.0,<6.0.0) ; extra == "redis" or extra == "all"
Requires-Dist: starlette (>=0.36.0,<0.37.0) ; extra == "fastapi" or extra == "all"
Project-URL: Documentation, https://github.com/mymi14s/frappe-auth-bridge#readme
Project-URL: Repository, https://github.com/mymi14s/frappe-auth-bridge
